fastfeatureflag/__init__.py
fastfeatureflag/__version__.py
fastfeatureflag/config.py
fastfeatureflag/errors.py
fastfeatureflag/feature_content.py
fastfeatureflag/feature_flag.py
fastfeatureflag/feature_flag_configuration.py
fastfeatureflag/shadow_configuration.py
fastfeatureflag-0.4.1.dist-info/LICENSE
fastfeatureflag-0.4.1.dist-info/METADATA
fastfeatureflag-0.4.1.dist-info/WHEEL
fastfeatureflag-0.4.1.dist-info/RECORD
