Metadata-Version: 2.1
Name: fastfeatureflag
Version: 0.4.1
Summary: light-weight feature flags
Home-page: https://grenait.github.io/fastfeatureflag/
License: MIT
Author: GreNait
Requires-Python: >=3.10,<4.0
Classifier: License :: OSI Approved :: MIT License
Classifier: Programming Language :: Python :: 3
Classifier: Programming Language :: Python :: 3.10
Classifier: Programming Language :: Python :: 3.11
Requires-Dist: anyio (>=3.7.1,<4.0.0)
Requires-Dist: python-dotenv (>=1.0.0,<2.0.0)
Requires-Dist: toml (>=0.10.2,<0.11.0)
Requires-Dist: types-toml (>=0.10.8.7,<0.11.0.0)
Project-URL: Repository, https://github.com/GreNait/fastfeatureflag
